[
    {
        "exitcode": 0,
        "id": "136.7721",
        "known_error": 0,
        "name": "RunJetHT2016H_reminiaod+RunJetHT2016H_reminiaod+REMINIAOD_data2016+HARVESTDR2_REMINIAOD_data2016",
        "steps": [
            {
                "errors": 0,
                "status": "PASSED",
                "warnings": 0
            },
            {
                "errors": 8,
                "status": "PASSED",
                "warnings": 311
            },
            {
                "errors": 0,
                "status": "PASSED",
                "warnings": 0
            }
        ]
    },
    {
        "exitcode": 0,
        "id": "136.867",
        "known_error": 0,
        "name": "RunSingleMu2018B+RunSingleMu2018B+HLTDR2_2018+RECODR2_2018reHLT_skimSingleMu_Offline_Lumi+HARVEST2018_L1TMuDQM",
        "steps": [
            {
                "errors": 0,
                "status": "PASSED",
                "warnings": 0
            },
            {
                "errors": 0,
                "status": "PASSED",
                "warnings": 108
            },
            {
                "errors": 10,
                "status": "PASSED",
                "warnings": 845
            },
            {
                "errors": 3,
                "status": "PASSED",
                "warnings": 4
            }
        ]
    },
    {
        "exitcode": 0,
        "id": "1329.1",
        "known_error": 0,
        "name": "ZEE_13_80XNanoAODINPUT+ZEE_13_80XNanoAODINPUT+NANOEDMMC2016_80X+HARVESTNANOAODMC2016_80X",
        "steps": [
            {
                "errors": 0,
                "status": "PASSED",
                "warnings": 0
            },
            {
                "errors": 8,
                "status": "PASSED",
                "warnings": 254
            },
            {
                "errors": 0,
                "status": "PASSED",
                "warnings": 0
            }
        ]
    },
    {
        "exitcode": 0,
        "id": "25406.0",
        "known_error": 0,
        "name": "ZMM_13+FS_ZMM_13_UP15_PU25+HARVESTUP15FS+MINIAODMCUP15FS",
        "steps": [
            {
                "errors": 3,
                "status": "PASSED",
                "warnings": 359
            },
            {
                "errors": 24,
                "status": "PASSED",
                "warnings": 0
            },
            {
                "errors": 16,
                "status": "PASSED",
                "warnings": 0
            }
        ]
    }
]
