{
  "avg": {
    "217": [
      "136.888501"
    ], 
    "237": [
      "2017.13"
    ], 
    "242": [
      "136.899"
    ], 
    "246": [
      "1307.0"
    ], 
    "253": [
      "1329.1"
    ], 
    "265": [
      "1325.1"
    ], 
    "274": [
      "140.53"
    ], 
    "280": [
      "10842.501"
    ], 
    "284": [
      "10824.501"
    ], 
    "286": [
      "140.5611"
    ], 
    "287": [
      "10824.5", 
      "4.22"
    ], 
    "289": [
      "1325.3"
    ], 
    "291": [
      "136.72411"
    ], 
    "298": [
      "140.51"
    ], 
    "306": [
      "135.12"
    ], 
    "307": [
      "10824.505"
    ], 
    "311": [
      "10024.5"
    ], 
    "312": [
      "136.77211"
    ], 
    "316": [
      "1325.516"
    ], 
    "317": [
      "135.5"
    ], 
    "319": [
      "1325.61"
    ], 
    "321": [
      "135.1", 
      "250403.0"
    ], 
    "324": [
      "250406.0"
    ], 
    "325": [
      "250402.181"
    ], 
    "326": [
      "2018.5", 
      "138.4", 
      "136.7611"
    ], 
    "327": [
      "135.4", 
      "1325.5161", 
      "250408.0", 
      "2017.2"
    ], 
    "329": [
      "2018.7", 
      "2017.5"
    ], 
    "331": [
      "135.6", 
      "135.2", 
      "2018.4"
    ], 
    "333": [
      "2018.3", 
      "135.3", 
      "158.01", 
      "250402.1"
    ], 
    "334": [
      "2017.12"
    ], 
    "336": [
      "136.72412", 
      "136.8521"
    ], 
    "341": [
      "11634.521", 
      "11634.511"
    ], 
    "343": [
      "135.9", 
      "250405.18", 
      "136.88811"
    ], 
    "345": [
      "136.8311", 
      "2017.3"
    ], 
    "346": [
      "136.7721", 
      "250402.18", 
      "1003.0"
    ], 
    "347": [
      "135.7", 
      "250400.17", 
      "2017.4"
    ], 
    "348": [
      "10842.505"
    ], 
    "349": [
      "13240.303", 
      "250407.18"
    ], 
    "350": [
      "250406.17", 
      "250402.0"
    ], 
    "352": [
      "250405.0"
    ], 
    "353": [
      "2017.6", 
      "2018.12"
    ], 
    "355": [
      "136.83111", 
      "136.8522"
    ], 
    "356": [
      "250400.0", 
      "250402.17"
    ], 
    "357": [
      "250408.17", 
      "250403.17"
    ], 
    "358": [
      "2017.7"
    ], 
    "359": [
      "135.11", 
      "2018.11"
    ], 
    "360": [
      "136.76111"
    ], 
    "362": [
      "25406.0"
    ], 
    "363": [
      "2017.9"
    ], 
    "368": [
      "250407.17", 
      "140.54"
    ], 
    "369": [
      "2018.2"
    ], 
    "370": [
      "250402.171"
    ], 
    "373": [
      "2017.11"
    ], 
    "374": [
      "250406.18", 
      "1325.51", 
      "25403.0"
    ], 
    "375": [
      "250408.18", 
      "2017.1"
    ], 
    "376": [
      "25406.17"
    ], 
    "379": [
      "250405.17"
    ], 
    "381": [
      "7.0"
    ], 
    "382": [
      "140.52"
    ], 
    "383": [
      "250403.18", 
      "25400.0"
    ], 
    "384": [
      "250409.0", 
      "250407.0"
    ], 
    "389": [
      "11634.5"
    ], 
    "392": [
      "1325.517"
    ], 
    "393": [
      "250409.17", 
      "250400.18"
    ], 
    "395": [
      "250409.18"
    ], 
    "396": [
      "2018.9", 
      "1325.5"
    ], 
    "397": [
      "25407.0", 
      "1325.518", 
      "510.0"
    ], 
    "398": [
      "7.22", 
      "25405.0"
    ], 
    "401": [
      "1325.81"
    ], 
    "407": [
      "1.0"
    ], 
    "408": [
      "10024.3"
    ], 
    "412": [
      "2018.1"
    ], 
    "415": [
      "503.0"
    ], 
    "416": [
      "1030.0"
    ], 
    "421": [
      "2018.6"
    ], 
    "422": [
      "10024.1"
    ], 
    "428": [
      "10824.1"
    ], 
    "429": [
      "1301.0"
    ], 
    "438": [
      "25409.0"
    ], 
    "440": [
      "1325.6", 
      "11634.501"
    ], 
    "456": [
      "25402.0"
    ], 
    "467": [
      "11650.501"
    ], 
    "478": [
      "11634.505"
    ], 
    "483": [
      "7.1"
    ], 
    "488": [
      "1325.7"
    ], 
    "497": [
      "25406.18"
    ], 
    "514": [
      "39434.5"
    ], 
    "560": [
      "128.0"
    ], 
    "608": [
      "21.0"
    ], 
    "791": [
      "23234.0"
    ], 
    "795": [
      "136.793"
    ], 
    "810": [
      "139.003"
    ], 
    "818": [
      "136.8"
    ], 
    "819": [
      "136.814"
    ], 
    "822": [
      "250204.0"
    ], 
    "826": [
      "10809.0"
    ], 
    "827": [
      "136.753", 
      "136.807"
    ], 
    "831": [
      "136.738"
    ], 
    "837": [
      "136.795"
    ], 
    "840": [
      "10059.0"
    ], 
    "845": [
      "250202.0"
    ], 
    "855": [
      "39434.9"
    ], 
    "862": [
      "1001.2"
    ], 
    "863": [
      "136.792"
    ], 
    "875": [
      "1370.18"
    ], 
    "876": [
      "136.86"
    ], 
    "878": [
      "136.884"
    ], 
    "895": [
      "10859.0"
    ], 
    "911": [
      "136.805"
    ], 
    "915": [
      "136.852"
    ], 
    "920": [
      "136.857"
    ], 
    "923": [
      "39434.0"
    ], 
    "931": [
      "136.808", 
      "136.786"
    ], 
    "933": [
      "136.841"
    ], 
    "934": [
      "136.784"
    ], 
    "948": [
      "136.853"
    ], 
    "950": [
      "136.75"
    ], 
    "952": [
      "1370.17"
    ], 
    "968": [
      "136.78"
    ], 
    "972": [
      "136.768"
    ], 
    "977": [
      "136.758"
    ], 
    "980": [
      "136.739"
    ], 
    "982": [
      "250203.17"
    ], 
    "999": [
      "136.862"
    ], 
    "1004": [
      "139.002"
    ], 
    "1010": [
      "136.811"
    ], 
    "1011": [
      "11024.6"
    ], 
    "1033": [
      "136.875"
    ], 
    "1034": [
      "136.881"
    ], 
    "1041": [
      "136.878"
    ], 
    "1043": [
      "11601.0"
    ], 
    "1045": [
      "136.874"
    ], 
    "1048": [
      "136.893"
    ], 
    "1049": [
      "11025.0"
    ], 
    "1050": [
      "136.889", 
      "136.891"
    ], 
    "1053": [
      "11024.0"
    ], 
    "1055": [
      "136.892"
    ], 
    "1056": [
      "136.763", 
      "250200.182"
    ], 
    "1059": [
      "136.765"
    ], 
    "1062": [
      "12034.0"
    ], 
    "1063": [
      "11024.2", 
      "136.868"
    ], 
    "1064": [
      "136.781", 
      "11634.7"
    ], 
    "1073": [
      "136.82"
    ], 
    "1080": [
      "250202.172"
    ], 
    "1082": [
      "136.817"
    ], 
    "1087": [
      "136.872"
    ], 
    "1088": [
      "136.8862"
    ], 
    "1090": [
      "11634.91"
    ], 
    "1102": [
      "11602.0", 
      "250204.17"
    ], 
    "1103": [
      "136.822", 
      "136.895"
    ], 
    "1104": [
      "136.8501", 
      "11643.0"
    ], 
    "1105": [
      "11603.0"
    ], 
    "1107": [
      "11725.0"
    ], 
    "1110": [
      "250206.17"
    ], 
    "1111": [
      "11607.0"
    ], 
    "1113": [
      "25215.18"
    ], 
    "1115": [
      "11640.0"
    ], 
    "1116": [
      "136.859"
    ], 
    "1118": [
      "11604.0"
    ], 
    "1122": [
      "136.764"
    ], 
    "1123": [
      "11024.15"
    ], 
    "1126": [
      "11630.0"
    ], 
    "1129": [
      "136.867"
    ], 
    "1131": [
      "11608.0"
    ], 
    "1132": [
      "136.863"
    ], 
    "1135": [
      "136.8391"
    ], 
    "1139": [
      "136.782"
    ], 
    "1141": [
      "11605.0"
    ], 
    "1145": [
      "11634.15"
    ], 
    "1149": [
      "136.783"
    ], 
    "1159": [
      "11650.0"
    ], 
    "1162": [
      "250202.182"
    ], 
    "1170": [
      "136.896"
    ], 
    "1179": [
      "136.877"
    ], 
    "1210": [
      "250202.3"
    ], 
    "1212": [
      "136.888"
    ], 
    "1234": [
      "12834.0"
    ], 
    "1240": [
      "250202.5"
    ], 
    "1265": [
      "158.0"
    ], 
    "1270": [
      "136.818"
    ], 
    "1316": [
      "136.76"
    ], 
    "1365": [
      "139.005"
    ], 
    "1512": [
      "140.56"
    ], 
    "1534": [
      "250203.18"
    ], 
    "1573": [
      "250207.18"
    ], 
    "1628": [
      "250200.18"
    ]
  }, 
  "workflows": {
    "1.0": [
      407
    ], 
    "1001.2": [
      862
    ], 
    "10024.1": [
      422
    ], 
    "10024.3": [
      408
    ], 
    "10024.5": [
      311
    ], 
    "1003.0": [
      346
    ], 
    "10059.0": [
      840
    ], 
    "1030.0": [
      416
    ], 
    "10809.0": [
      826
    ], 
    "10824.1": [
      428
    ], 
    "10824.5": [
      287
    ], 
    "10824.501": [
      284
    ], 
    "10824.505": [
      307
    ], 
    "10842.501": [
      280
    ], 
    "10842.505": [
      348
    ], 
    "10859.0": [
      895
    ], 
    "11024.0": [
      1053
    ], 
    "11024.15": [
      1123
    ], 
    "11024.2": [
      1063
    ], 
    "11024.6": [
      1011
    ], 
    "11025.0": [
      1049
    ], 
    "11601.0": [
      1043
    ], 
    "11602.0": [
      1102
    ], 
    "11603.0": [
      1105
    ], 
    "11604.0": [
      1118
    ], 
    "11605.0": [
      1141
    ], 
    "11607.0": [
      1111
    ], 
    "11608.0": [
      1131
    ], 
    "11630.0": [
      1126
    ], 
    "11634.15": [
      1145
    ], 
    "11634.5": [
      389
    ], 
    "11634.501": [
      440
    ], 
    "11634.505": [
      478
    ], 
    "11634.511": [
      341
    ], 
    "11634.521": [
      341
    ], 
    "11634.7": [
      1064
    ], 
    "11634.91": [
      1090
    ], 
    "11640.0": [
      1115
    ], 
    "11643.0": [
      1104
    ], 
    "11650.0": [
      1159
    ], 
    "11650.501": [
      467
    ], 
    "11725.0": [
      1107
    ], 
    "12034.0": [
      1062
    ], 
    "128.0": [
      560
    ], 
    "12834.0": [
      1234
    ], 
    "1301.0": [
      429
    ], 
    "1307.0": [
      246
    ], 
    "13240.303": [
      349
    ], 
    "1325.1": [
      265
    ], 
    "1325.3": [
      289
    ], 
    "1325.5": [
      396
    ], 
    "1325.51": [
      374
    ], 
    "1325.516": [
      316
    ], 
    "1325.5161": [
      327
    ], 
    "1325.517": [
      392
    ], 
    "1325.518": [
      397
    ], 
    "1325.6": [
      440
    ], 
    "1325.61": [
      319
    ], 
    "1325.7": [
      488
    ], 
    "1325.81": [
      401
    ], 
    "1329.1": [
      253
    ], 
    "135.1": [
      321
    ], 
    "135.11": [
      359
    ], 
    "135.12": [
      306
    ], 
    "135.2": [
      331
    ], 
    "135.3": [
      333
    ], 
    "135.4": [
      327
    ], 
    "135.5": [
      317
    ], 
    "135.6": [
      331
    ], 
    "135.7": [
      347
    ], 
    "135.9": [
      343
    ], 
    "136.72411": [
      291
    ], 
    "136.72412": [
      336
    ], 
    "136.738": [
      831
    ], 
    "136.739": [
      980
    ], 
    "136.75": [
      950
    ], 
    "136.753": [
      827
    ], 
    "136.758": [
      977
    ], 
    "136.76": [
      1316
    ], 
    "136.7611": [
      326
    ], 
    "136.76111": [
      360
    ], 
    "136.763": [
      1056
    ], 
    "136.764": [
      1122
    ], 
    "136.765": [
      1059
    ], 
    "136.768": [
      972
    ], 
    "136.7721": [
      346
    ], 
    "136.77211": [
      312
    ], 
    "136.78": [
      968
    ], 
    "136.781": [
      1064
    ], 
    "136.782": [
      1139
    ], 
    "136.783": [
      1149
    ], 
    "136.784": [
      934
    ], 
    "136.786": [
      931
    ], 
    "136.792": [
      863
    ], 
    "136.793": [
      795
    ], 
    "136.795": [
      837
    ], 
    "136.8": [
      818
    ], 
    "136.805": [
      911
    ], 
    "136.807": [
      827
    ], 
    "136.808": [
      931
    ], 
    "136.811": [
      1010
    ], 
    "136.814": [
      819
    ], 
    "136.817": [
      1082
    ], 
    "136.818": [
      1270
    ], 
    "136.82": [
      1073
    ], 
    "136.822": [
      1103
    ], 
    "136.8311": [
      345
    ], 
    "136.83111": [
      355
    ], 
    "136.8391": [
      1135
    ], 
    "136.841": [
      933
    ], 
    "136.8501": [
      1104
    ], 
    "136.852": [
      915
    ], 
    "136.8521": [
      336
    ], 
    "136.8522": [
      355
    ], 
    "136.853": [
      948
    ], 
    "136.857": [
      920
    ], 
    "136.859": [
      1116
    ], 
    "136.86": [
      876
    ], 
    "136.862": [
      999
    ], 
    "136.863": [
      1132
    ], 
    "136.867": [
      1129
    ], 
    "136.868": [
      1063
    ], 
    "136.872": [
      1087
    ], 
    "136.874": [
      1045
    ], 
    "136.875": [
      1033
    ], 
    "136.877": [
      1179
    ], 
    "136.878": [
      1041
    ], 
    "136.881": [
      1034
    ], 
    "136.884": [
      878
    ], 
    "136.8862": [
      1088
    ], 
    "136.888": [
      1212
    ], 
    "136.88811": [
      343
    ], 
    "136.888501": [
      217
    ], 
    "136.889": [
      1050
    ], 
    "136.891": [
      1050
    ], 
    "136.892": [
      1055
    ], 
    "136.893": [
      1048
    ], 
    "136.895": [
      1103
    ], 
    "136.896": [
      1170
    ], 
    "136.899": [
      242
    ], 
    "1370.17": [
      952
    ], 
    "1370.18": [
      875
    ], 
    "138.4": [
      326
    ], 
    "139.002": [
      1004
    ], 
    "139.003": [
      810
    ], 
    "139.005": [
      1365
    ], 
    "140.51": [
      298
    ], 
    "140.52": [
      382
    ], 
    "140.53": [
      274
    ], 
    "140.54": [
      368
    ], 
    "140.56": [
      1512
    ], 
    "140.5611": [
      286
    ], 
    "158.0": [
      1265
    ], 
    "158.01": [
      333
    ], 
    "2017.1": [
      375
    ], 
    "2017.11": [
      373
    ], 
    "2017.12": [
      334
    ], 
    "2017.13": [
      237
    ], 
    "2017.2": [
      327
    ], 
    "2017.3": [
      345
    ], 
    "2017.4": [
      347
    ], 
    "2017.5": [
      329
    ], 
    "2017.6": [
      353
    ], 
    "2017.7": [
      358
    ], 
    "2017.9": [
      363
    ], 
    "2018.1": [
      412
    ], 
    "2018.11": [
      359
    ], 
    "2018.12": [
      353
    ], 
    "2018.2": [
      369
    ], 
    "2018.3": [
      333
    ], 
    "2018.4": [
      331
    ], 
    "2018.5": [
      326
    ], 
    "2018.6": [
      421
    ], 
    "2018.7": [
      329
    ], 
    "2018.9": [
      396
    ], 
    "21.0": [
      608
    ], 
    "23234.0": [
      791
    ], 
    "250200.18": [
      1628
    ], 
    "250200.182": [
      1056
    ], 
    "250202.0": [
      845
    ], 
    "250202.172": [
      1080
    ], 
    "250202.182": [
      1162
    ], 
    "250202.3": [
      1210
    ], 
    "250202.5": [
      1240
    ], 
    "250203.17": [
      982
    ], 
    "250203.18": [
      1534
    ], 
    "250204.0": [
      822
    ], 
    "250204.17": [
      1102
    ], 
    "250206.17": [
      1110
    ], 
    "250207.18": [
      1573
    ], 
    "250400.0": [
      356
    ], 
    "250400.17": [
      347
    ], 
    "250400.18": [
      393
    ], 
    "250402.0": [
      350
    ], 
    "250402.1": [
      333
    ], 
    "250402.17": [
      356
    ], 
    "250402.171": [
      370
    ], 
    "250402.18": [
      346
    ], 
    "250402.181": [
      325
    ], 
    "250403.0": [
      321
    ], 
    "250403.17": [
      357
    ], 
    "250403.18": [
      383
    ], 
    "250405.0": [
      352
    ], 
    "250405.17": [
      379
    ], 
    "250405.18": [
      343
    ], 
    "250406.0": [
      324
    ], 
    "250406.17": [
      350
    ], 
    "250406.18": [
      374
    ], 
    "250407.0": [
      384
    ], 
    "250407.17": [
      368
    ], 
    "250407.18": [
      349
    ], 
    "250408.0": [
      327
    ], 
    "250408.17": [
      357
    ], 
    "250408.18": [
      375
    ], 
    "250409.0": [
      384
    ], 
    "250409.17": [
      393
    ], 
    "250409.18": [
      395
    ], 
    "25215.18": [
      1113
    ], 
    "25400.0": [
      383
    ], 
    "25402.0": [
      456
    ], 
    "25403.0": [
      374
    ], 
    "25405.0": [
      398
    ], 
    "25406.0": [
      362
    ], 
    "25406.17": [
      376
    ], 
    "25406.18": [
      497
    ], 
    "25407.0": [
      397
    ], 
    "25409.0": [
      438
    ], 
    "39434.0": [
      923
    ], 
    "39434.5": [
      514
    ], 
    "39434.9": [
      855
    ], 
    "4.22": [
      287
    ], 
    "503.0": [
      415
    ], 
    "510.0": [
      397
    ], 
    "7.0": [
      381
    ], 
    "7.1": [
      483
    ], 
    "7.22": [
      398
    ]
  }
}
