{
  "avg": {
    "69": [
      "11634.504"
    ], 
    "70": [
      "11650.504"
    ], 
    "88": [
      "11634.524", 
      "11634.508"
    ], 
    "95": [
      "11650.508"
    ], 
    "97": [
      "11634.514"
    ], 
    "107": [
      "12434.524"
    ], 
    "108": [
      "12450.504"
    ], 
    "109": [
      "12434.514", 
      "12450.508"
    ], 
    "112": [
      "12434.504"
    ], 
    "113": [
      "12434.508"
    ], 
    "125": [
      "11634.523", 
      "11634.513"
    ], 
    "126": [
      "11634.512", 
      "11634.522"
    ], 
    "133": [
      "11650.507", 
      "11650.506", 
      "11650.502", 
      "11634.502"
    ], 
    "134": [
      "11634.506", 
      "11650.503"
    ], 
    "136": [
      "11634.503"
    ], 
    "138": [
      "11634.507", 
      "11634.582"
    ], 
    "139": [
      "11634.586"
    ], 
    "140": [
      "11634.587"
    ], 
    "141": [
      "11634.583"
    ], 
    "167": [
      "12434.522"
    ], 
    "168": [
      "12434.513", 
      "12434.512", 
      "12434.523"
    ], 
    "173": [
      "12450.506", 
      "12450.502"
    ], 
    "174": [
      "12434.502"
    ], 
    "175": [
      "12434.586", 
      "12434.506", 
      "12450.507"
    ], 
    "176": [
      "12434.582", 
      "12434.503", 
      "12434.507"
    ], 
    "177": [
      "12450.503"
    ], 
    "178": [
      "12434.583"
    ], 
    "179": [
      "12434.587"
    ], 
    "196": [
      "140.065512"
    ], 
    "197": [
      "140.065522"
    ], 
    "201": [
      "140.065506"
    ], 
    "278": [
      "11634.597"
    ], 
    "279": [
      "11634.592"
    ], 
    "287": [
      "11634.593"
    ], 
    "312": [
      "11634.596"
    ], 
    "365": [
      "12434.596"
    ], 
    "376": [
      "12434.597"
    ], 
    "377": [
      "12434.592"
    ], 
    "378": [
      "12434.593"
    ]
  }, 
  "workflows": {
    "11634.502": [
      139, 
      145, 
      114, 
      135
    ], 
    "11634.503": [
      141, 
      146, 
      118, 
      142
    ], 
    "11634.504": [
      71, 
      76, 
      63, 
      69
    ], 
    "11634.506": [
      143, 
      144, 
      118, 
      132
    ], 
    "11634.507": [
      144, 
      146, 
      120, 
      143
    ], 
    "11634.508": [
      71, 
      154, 
      61, 
      69
    ], 
    "11634.512": [
      135, 
      135, 
      109, 
      127
    ], 
    "11634.513": [
      132, 
      135, 
      108, 
      127
    ], 
    "11634.514": [
      75, 
      185, 
      60, 
      71
    ], 
    "11634.522": [
      132, 
      137, 
      108, 
      130
    ], 
    "11634.523": [
      133, 
      136, 
      107, 
      126
    ], 
    "11634.524": [
      74, 
      151, 
      60, 
      70
    ], 
    "11634.582": [
      147, 
      145, 
      122, 
      140
    ], 
    "11634.583": [
      152, 
      151, 
      126, 
      138
    ], 
    "11634.586": [
      149, 
      150, 
      121, 
      139
    ], 
    "11634.587": [
      148, 
      152, 
      125, 
      137
    ], 
    "11634.592": [
      269, 
      269, 
      256, 
      325
    ], 
    "11634.593": [
      274, 
      273, 
      253, 
      348
    ], 
    "11634.596": [
      269, 
      300, 
      267, 
      413
    ], 
    "11634.597": [
      269, 
      269, 
      255, 
      319
    ], 
    "11650.502": [
      143, 
      142, 
      114, 
      135
    ], 
    "11650.503": [
      140, 
      146, 
      113, 
      137
    ], 
    "11650.504": [
      73, 
      74, 
      62, 
      73
    ], 
    "11650.506": [
      143, 
      141, 
      115, 
      133
    ], 
    "11650.507": [
      139, 
      143, 
      116, 
      135
    ], 
    "11650.508": [
      69, 
      185, 
      61, 
      68
    ], 
    "12434.502": [
      185, 
      187, 
      152, 
      172
    ], 
    "12434.503": [
      185, 
      190, 
      158, 
      174
    ], 
    "12434.504": [
      115, 
      125, 
      99, 
      112
    ], 
    "12434.506": [
      186, 
      184, 
      153, 
      178
    ], 
    "12434.507": [
      188, 
      185, 
      155, 
      178
    ], 
    "12434.508": [
      116, 
      125, 
      100, 
      111
    ], 
    "12434.512": [
      178, 
      179, 
      147, 
      171
    ], 
    "12434.513": [
      176, 
      179, 
      148, 
      170
    ], 
    "12434.514": [
      113, 
      115, 
      97, 
      111
    ], 
    "12434.522": [
      179, 
      176, 
      146, 
      168
    ], 
    "12434.523": [
      179, 
      180, 
      147, 
      168
    ], 
    "12434.524": [
      110, 
      114, 
      99, 
      108
    ], 
    "12434.582": [
      185, 
      191, 
      155, 
      174
    ], 
    "12434.583": [
      191, 
      187, 
      158, 
      177
    ], 
    "12434.586": [
      190, 
      184, 
      155, 
      173
    ], 
    "12434.587": [
      187, 
      189, 
      158, 
      182
    ], 
    "12434.592": [
      410, 
      387, 
      346, 
      365
    ], 
    "12434.593": [
      413, 
      386, 
      351, 
      365
    ], 
    "12434.596": [
      387, 
      363, 
      346, 
      365
    ], 
    "12434.597": [
      406, 
      386, 
      349, 
      365
    ], 
    "12450.502": [
      182, 
      185, 
      155, 
      172
    ], 
    "12450.503": [
      188, 
      181, 
      159, 
      181
    ], 
    "12450.504": [
      114, 
      111, 
      98, 
      112
    ], 
    "12450.506": [
      187, 
      182, 
      151, 
      172
    ], 
    "12450.507": [
      184, 
      189, 
      151, 
      177
    ], 
    "12450.508": [
      114, 
      114, 
      98, 
      111
    ], 
    "140.065506": [
      211, 
      214, 
      183, 
      198
    ], 
    "140.065512": [
      205, 
      205, 
      177, 
      199
    ], 
    "140.065522": [
      205, 
      205, 
      180, 
      199
    ]
  }
}
